setup.cfg
setup.py
statstable/__init__.py
statstable/ss.py
statstable.egg-info/PKG-INFO
statstable.egg-info/SOURCES.txt
statstable.egg-info/dependency_links.txt
statstable.egg-info/requires.txt
statstable.egg-info/top_level.txt