Metadata-Version: 1.1
Name: statstable
Version: 0.2
Summary: A wrapper to the StatStable API to retreive sports statistics
Home-page: https://github.com/statstable/statstable-python
Author: StatStable
Author-email: info@statstable.com
License: UNKNOWN
Download-URL: https://github.com/statstable/statstable-python/archive/0.2.tar.gz
Keywords: statstable,api,wrapper,sports,statistics,nba,mlb
Platform: UNKNOWN
